{"trial_id": "2", "hyperparameters": {"space": [{"class_name": "Choice", "config": {"name": "conv1_filters", "default": 16, "conditions": [], "values": [16, 32], "ordered": true}}, {"class_name": "Choice", "config": {"name": "conv2_filters", "default": 32, "conditions": [], "values": [32, 64], "ordered": true}}, {"class_name": "Choice", "config": {"name": "conv3_filters", "default": 64, "conditions": [], "values": [64, 128], "ordered": true}}, {"class_name": "Choice", "config": {"name": "dense1_units", "default": 128, "conditions": [], "values": [128, 256, 512], "ordered": true}}, {"class_name": "Choice", "config": {"name": "dropout1", "default": 0.25, "conditions": [], "values": [0.25, 0.3, 0.4], "ordered": true}}, {"class_name": "Choice", "config": {"name": "dense2_units", "default": 64, "conditions": [], "values": [64, 128], "ordered": true}}, {"class_name": "Choice", "config": {"name": "dropout2", "default": 0.25, "conditions": [], "values": [0.25, 0.3], "ordered": true}}, {"class_name": "Choice", "config": {"name": "learning_rate", "default": 0.01, "conditions": [], "values": [0.01, 0.001, 0.0001], "ordered": true}}], "values": {"conv1_filters": 32, "conv2_filters": 32, "conv3_filters": 64, "dense1_units": 512, "dropout1": 0.4, "dense2_units": 64, "dropout2": 0.3, "learning_rate": 0.01}}, "metrics": {"metrics": {"accuracy": {"direction": "max", "observations": [{"value": [0.47715455293655396], "step": 6}]}, "loss": {"direction": "min", "observations": [{"value": [0.27050986886024475], "step": 6}]}, "val_accuracy": {"direction": "max", "observations": [{"value": [0.46500593423843384], "step": 6}]}, "val_loss": {"direction": "min", "observations": [{"value": [0.32037317752838135], "step": 6}]}}}, "score": 0.46500593423843384, "best_step": 6, "status": "COMPLETED", "message": null}